{
  "kind": "collectionType",
  "collectionName": "services",
  "info": {
    "singularName": "service",
    "pluralName": "services",
    "displayName": "service"
  },
  "options": {
    "draftAndPublish": true
  },
  "pluginOptions": {},
  "attributes": {
    "title": {
      "type": "string",
      "required": true
    },
    "slug": {
      "type": "uid",
      "targetField": "title",
      "required": true
    },
    "cover": {
      "type": "media",
      "multiple": false,
      "allowedTypes": [
        "images",
        "files",
        "videos",
        "audios"
      ]
    },
    "description": {
      "type": "text"
    },
    "widgets": {
      "type": "dynamiczone",
      "components": [
        "widgets.inner-banner",
        "widgets.home-testimonials",
        "widgets.home-stat",
        "widgets.home-spec",
        "widgets.home-services",
        "widgets.home-faq",
        "widgets.home-doctors",
        "widgets.home-clients",
        "widgets.home-choose",
        "widgets.home-blogs",
        "widgets.home-banner",
        "widgets.home-about",
        "widgets.featured-blogs",
        "widgets.doctors-single-banner",
        "widgets.doctors-detail",
        "widgets.doctors-content",
        "widgets.detail-widget",
        "widgets.cta-section",
        "widgets.blog-listing",
        "widgets.service-about",
        "widgets.content-sec",
        "widgets.service-banner"
      ]
    },
    "seo": {
      "type": "component",
      "component": "shared.seo",
      "repeatable": false
    }
  }
}
